{
  "ok": true,
  "matchId": "02SQ12DL00000000VS5489B4VTF03LPG",
  "url": "https://www.fussball.de/spiel/sc-hassel-ii-yeg-hasselii/-/spiel/02SQ12DL00000000VS5489B4VTF03LPG",
  "home": "SC Hassel II",
  "away": "YEG HASSELII",
  "ownSide": "home",
  "count": 9,
  "players": [
    {
      "id": "home___",
      "matchId": "02SQ12DL00000000VS5489B4VTF03LPG",
      "side": "home",
      "name": "Mahmut Aydin",
      "rawName": "оұҠо®җоӯ…оўҫоңјојЈ пҒ№оӣӢпӮ„оұЁоЁӯ",
      "number": "",
      "img": "",
      "obfuscationKey": "p8wajqlz"
    }
  ],
  "stableId": "02SQ12DL00000000VS5489B4VTF03LPG",
  "generatedAt": "2026-04-07T06:14:04.890Z",
  "game": {
    "home": "SC Hassel II",
    "away": "YEG HASSELII",
    "date": "05.07.2025",
    "time": "13:48",
    "competition": "Vereinsturnier",
    "ageGroup": "",
    "spielId": "02SQ12DL00000000VS5489B4VTF03LPG"
  }
}