{
  "ok": true,
  "matchId": "02TMOG4HGC000000VS5489BUVSSD35NB",
  "url": "https://www.fussball.de/spiel/sc-hassel-sc-hassel/-/spiel/02TMOG4HGC000000VS5489BUVSSD35NB",
  "home": "SC Hassel",
  "away": "SC Hassel",
  "ownSide": "home",
  "count": 17,
  "players": [
    {
      "id": "02R65IJHMS000000VUM1D56KVVQNETJA",
      "matchId": "02TMOG4HGC000000VS5489BUVSSD35NB",
      "side": "home",
      "name": "Nico Albrecht",
      "rawName": "оҝ оҘҪоәЁоЈ· оҹ№оӣҠо®ӯоёҷпҖҶоәЁо»‘оҹ„",
      "number": "01",
      "img": "https://cdn.fussball.de/public/0302EJHJTG000000VS5489C2VUQHFANL.stamp",
      "obfuscationKey": "dqe9usuk"
    },
    {
      "id": "02QMD0JI58000000VUM1D570VSFEAFHL",
      "matchId": "02TMOG4HGC000000VS5489BUVSSD35NB",
      "side": "home",
      "name": "Adem Akkus",
      "rawName": "оҹ№о·ўоЁ№оӯ§ оҹ№оұӨоұӨојӢоқІ",
      "number": "04",
      "img": "//www.fussball.de/export.media/-/action/getPlayerImage/format/15/image-id/NPI_1234567890123456789012345678",
      "obfuscationKey": "dqe9usuk"
    },
    {
      "id": "02KSLESHK8000000VS5489B5VU0LQOOJ",
      "matchId": "02TMOG4HGC000000VS5489BUVSSD35NB",
      "side": "home",
      "name": "Yanislav Miklash",
      "rawName": "о№·о¬Ҹоҙёо«ҒоІҖоӣҠоҝ‘оӘІ о®—оҘҪоұӨоөҸоҝ‘оқІо»‘",
      "number": "07",
      "img": "https://cdn.fussball.de/public/02TDDU2A64000000VS5489BSVTA87VEB.stamp",
      "obfuscationKey": "dqe9usuk"
    },
    {
      "id": "01LUU13J7C000000VV0AG811VUC98CQT",
      "matchId": "02TMOG4HGC000000VS5489BUVSSD35NB",
      "side": "home",
      "name": "Devin Phil Berg",
      "rawName": "оҜўпҖҶпҖ“оҘҪоҙё оҫөоөҲоҘҪоӣҠ оұҢоЁ№оөЁоһё",
      "number": "08",
      "img": "https://cdn.fussball.de/public/02TI3ODHJ4000000VS5489C1VSGRS9TH.stamp",
      "obfuscationKey": "dqe9usuk"
    },
    {
      "id": "02MJHOSL2O000000VUM1DNOIVS7F3QJB",
      "matchId": "02TMOG4HGC000000VS5489BUVSSD35NB",
      "side": "home",
      "name": "Jonas Marcel Schumacher",
      "rawName": "оӯҳо¬Ҙоіқоҝ‘оІҖ о®—о¬ҸоёҷоӣәпҖҶоӣҠ оұёоәЁо»‘ојӢо§Ӣоҝ‘оәЁо»‘оЁ№оёҷ",
      "number": "09",
      "img": "https://images.media.fussball.de/userfiles/J/o/i/UPtaewaR5xZX6ctjYyp0iz_p3.jpg",
      "obfuscationKey": "dqe9usuk"
    },
    {
      "id": "028B09L09C000000VS5489B5VUCDA5G6",
      "matchId": "02TMOG4HGC000000VS5489BUVSSD35NB",
      "side": "home",
      "name": "Poyraz Metin Aydogan",
      "rawName": "оөҜоЈ·оЎ”оөЁоҝ‘оҡҪ оёӮоЁ№оӘҠоҘҪоіқ оҹ№о¶–оіҷоЈ·о«ҝо¬Ҹоҙё",
      "number": "11",
      "img": "https://cdn.fussball.de/public/02UG1DALDO000000VS5489BVVUQ9GB57.stamp",
      "obfuscationKey": "dqe9usuk"
    },
    {
      "id": "01LVKGSK48000000VV0AG80NVTMPTR0P",
      "matchId": "02TMOG4HGC000000VS5489BUVSSD35NB",
      "side": "home",
      "name": "Marcin Szydlowski",
      "rawName": "оёӮоҝ‘оёҷоӣәоҘҪоіқ оұёоҡҪо¶–о·ўоӣҠоЈ·оө»оқІоһҗоҘҪ",
      "number": "14",
      "img": "https://cdn.fussball.de/public/02UDK0P084000000VS5489BVVTFDUQ0U.stamp",
      "obfuscationKey": "dqe9usuk"
    },
    {
      "id": "02QN5J0RR0000000VUM1D53HVTL9MO41",
      "matchId": "02TMOG4HGC000000VS5489BUVSSD35NB",
      "side": "home",
      "name": "Bekir Veselji",
      "rawName": "оұҢпҖҶоһҗоҘҪоёҷ оІўоЁ№оқІоЁ№оөҸоіҙо«Ғ",
      "number": "17",
      "img": "https://cdn.fussball.de/public/02UDK1M3NK000000VS5489BVVTFDUQ0U.stamp",
      "obfuscationKey": "dqe9usuk"
    },
    {
      "id": "02C5AKQBTC000000VS5489B6VSIS19QJ",
      "matchId": "02TMOG4HGC000000VS5489BUVSSD35NB",
      "side": "home",
      "name": "Justin Favrin",
      "rawName": "оһІојӢоІҖоӘҠоҘҪоіқ оҡҝоҝ‘пҖ“оёҷо«Ғоҙё",
      "number": "18",
      "img": "https://cdn.fussball.de/public/02T0HCVOU8000000VS5489C0VS369459.stamp",
      "obfuscationKey": "dqe9usuk"
    },
    {
      "id": "02OGC8UAQ8000000VUM1DNO6VSU8RSKC",
      "matchId": "02TMOG4HGC000000VS5489BUVSSD35NB",
      "side": "home",
      "name": "Marvin Buchmann",
      "rawName": "оёӮо¬ҸоёҷоӘІоҘҪоҙё оұҢо»ҡоәЁо»‘оӯ§о¬Ҹоҙёоҙё",
      "number": "20",
      "img": "https://cdn.fussball.de/public/02UDJTH13O000000VS5489BVVTFDUQ0U.stamp",
      "obfuscationKey": "dqe9usuk"
    },
    {
      "id": "02ML4NU86K000000VUM1DNORVTA0CC9T",
      "matchId": "02TMOG4HGC000000VS5489BUVSSD35NB",
      "side": "home",
      "name": "Menderes Schortemeier",
      "rawName": "оёӮоЁ№оҙёоіҷоЁ№оөЁоЁ№оІҖ оұёоӣәоөҲоЈ·оөЁоҹ„оЁ№оӯ§пҖҶо«ҒоЁ№оөЁ",
      "number": "21",
      "img": "//www.fussball.de/export.media/-/action/getPlayerImage/format/15/image-id/NPI_1234567890123456789012345678",
      "obfuscationKey": "dqe9usuk"
    },
    {
      "id": "026U9Q6CM0000000VS5489B5VS8PA1JD",
      "matchId": "02TMOG4HGC000000VS5489BUVSSD35NB",
      "side": "home",
      "name": "Efe Kaan KГ¶se",
      "rawName": "о®Ғоұ’пҖҶ о®ҫоҝ‘о¬Ҹоҙё о®ҫоҡҹоқІпҖҶ",
      "number": "03",
      "img": "https://cdn.fussball.de/public/02PSTNND4O000000VS5489BBVURMFGV3.stamp",
      "obfuscationKey": "dqe9usuk"
    },
    {
      "id": "01ELSS4O5O000000VV0AG80NVVIPF5HD",
      "matchId": "02TMOG4HGC000000VS5489BUVSSD35NB",
      "side": "home",
      "name": "Adam Ait Hacene",
      "rawName": "оҹ№о·ўо¬Ҹоӯ§ оЈ•о«ҒоӘҠ оӨҙоҝ‘оәЁоЁ№оҙёоЁ№",
      "number": "10",
      "img": "https://cdn.fussball.de/public/0308CBDB64000000VS5489BVVSSE2MVC.stamp",
      "obfuscationKey": "dqe9usuk"
    },
    {
      "id": "02NID6MO00000000VUM1DNP7VU6DA5CP",
      "matchId": "02TMOG4HGC000000VS5489BUVSSD35NB",
      "side": "home",
      "name": "Mhd Nour Rabah",
      "rawName": "оёӮоөҲоіҷ оҝ о¬ҘојӢоёҷ оҡ•о¬Ҹо·—о¬Ҹо»‘",
      "number": "12",
      "img": "https://cdn.fussball.de/public/02UDJVTPQ8000000VS5489BVVTFDUQ0U.stamp",
      "obfuscationKey": "dqe9usuk"
    },
    {
      "id": "026HCDFQVO000000VS5489B6VU1J6RLI",
      "matchId": "02TMOG4HGC000000VS5489BUVSSD35NB",
      "side": "home",
      "name": "Mikail Zinxhiria",
      "rawName": "оёӮоҘҪоһҗоҝ‘о«ҒоӣҠ оіұоҘҪоҙёоЁӢо»‘оҘҪоөЁо«Ғоҝ‘",
      "number": "13",
      "img": "https://cdn.fussball.de/public/02UDK28C8S000000VS5489BVVTFDUQ0U.stamp",
      "obfuscationKey": "dqe9usuk"
    },
    {
      "id": "02G6D9K328000000VUM1DNQEVUU9RNE9",
      "matchId": "02TMOG4HGC000000VS5489BUVSSD35NB",
      "side": "home",
      "name": "Mustafa Enhar Coban",
      "rawName": "оёӮо»ҡоІҖоҹ„оҝ‘оұ’оҝ‘ оҘӢоҙёо»‘о¬Ҹоёҷ оЎӢо¬Ҙо·—о¬Ҹоіқ",
      "number": "16",
      "img": "https://images.media.fussball.de/userfiles/z/A/G/c0Eh9qloxjlOyUSdAzfSXz_p3.jpg",
      "obfuscationKey": "dqe9usuk"
    },
    {
      "id": "home___",
      "matchId": "02TMOG4HGC000000VS5489BUVSSD35NB",
      "side": "home",
      "name": "Holger Fabricius",
      "rawName": "о®ҖоЈ·оөҸо«ҝоЁ№оёҷ пҒ§оҝ‘о·—оөЁоҘҪоӣәоҘҪојӢоқІ",
      "number": "",
      "img": "",
      "obfuscationKey": "dqe9usuk"
    }
  ],
  "stableId": "02TMOG4HGC000000VS5489BUVSSD35NB",
  "generatedAt": "2026-04-07T06:14:04.890Z",
  "game": {
    "home": "SC Hassel",
    "away": "SC Hassel",
    "date": "13.07.2025",
    "time": "17:00",
    "competition": "Kreisfreundschaftsspiele",
    "ageGroup": "",
    "spielId": "02TMOG4HGC000000VS5489BUVSSD35NB"
  }
}