{
  "ok": true,
  "matchId": "02TQ6E3EPS000000VS5489BTVV0LE4BT",
  "url": "https://www.fussball.de/spiel/sv-zweckel-sc-hassel/-/spiel/02TQ6E3EPS000000VS5489BTVV0LE4BT",
  "home": "SV Zweckel",
  "away": "SC Hassel",
  "ownSide": "away",
  "count": 17,
  "players": [
    {
      "id": "023V09UDO4000000VS541L4IVTPV41CE",
      "matchId": "02TQ6E3EPS000000VS5489BTVV0LE4BT",
      "side": "away",
      "name": "Tom Altehage",
      "rawName": "๎กด๎ฅ๎ฝ ๎ข๎นบ๎บ ๎บ๎ฟ๎ปฃ๎ฑ๎ฎท",
      "number": "20",
      "img": "https://images.media.fussball.de/userfiles/6/8/a/9WukZ3zHylEOVQahYjL0Ya_p3.jpg",
      "obfuscationKey": "1cpqallx"
    },
    {
      "id": "016DLCHK30000000VV0AG80NVU5A0EBU",
      "matchId": "02TQ6E3EPS000000VS5489BTVV0LE4BT",
      "side": "away",
      "name": "Burak Gรผnes",
      "rawName": "๎น๏๎บญ๎ปฃ๎คณ ๎๎ณธ๎ฅง๎ฎท๎ฌ",
      "number": "22",
      "img": "https://cdn.fussball.de/public/02VKQDH1SO000000VS5489C0VTURPRAI.stamp",
      "obfuscationKey": "1cpqallx"
    },
    {
      "id": "00P1KHBNQS000000VV0AG83KVSA2TTUM",
      "matchId": "02TQ6E3EPS000000VS5489BTVV0LE4BT",
      "side": "away",
      "name": "Burak Aydin",
      "rawName": "๎ถ๏๎ญป๎ญท๎คณ ๎ธ๏๎ต๎ฏ๎ฅง",
      "number": "23",
      "img": "https://cdn.fussball.de/public/02S7PFG8GS000000VS5489B1VVVAF4P8.stamp",
      "obfuscationKey": "1cpqallx"
    },
    {
      "id": "00MC724DEO000000VV0AG85VVSMHI0R7",
      "matchId": "02TQ6E3EPS000000VS5489BTVV0LE4BT",
      "side": "away",
      "name": "Baris Aydin",
      "rawName": "๎ถ๎ปฃ๎บญ๎ฏ๎ฆ ๎ธ๎นฎ๎ต๎ตค๎ฅง",
      "number": "27",
      "img": "https://cdn.fussball.de/public/02VKIMLT4S000000VS5489C2VU4VO0A5.stamp",
      "obfuscationKey": "1cpqallx"
    },
    {
      "id": "02J7KRNHE8000000VUM1DNORVTH5RBQH",
      "matchId": "02TQ6E3EPS000000VS5489BTVV0LE4BT",
      "side": "away",
      "name": "Phil Kรผckelmann",
      "rawName": "๎ฒ๎ซฆ๎ตค๏ ๎ธ๎จ๎ท๎ฎน๎บ๏๎ถซ๎ญท๎ดฑ๎ดฑ",
      "number": "30",
      "img": "https://cdn.fussball.de/public/02VKINRUKO000000VS5489C2VU4VO0A5.stamp",
      "obfuscationKey": "1cpqallx"
    },
    {
      "id": "0266QS31K8000000VS541L4FVTTFAE2C",
      "matchId": "02TQ6E3EPS000000VS5489BTVV0LE4BT",
      "side": "away",
      "name": "Ergรผn Yalcin",
      "rawName": "๎ค๎ญป๎ฑ๎ณธ๎ฅง ๎ฎฐ๎ปฃ๏๎ท๎ฏ๎ฅง",
      "number": "01",
      "img": "//images.media.fussball.de/userfiles/D/a/7/wtgU0FWaSDzHgGCLF84zSa_p3.jpg",
      "obfuscationKey": "1cpqallx"
    },
    {
      "id": "01OG3IAP74000000VS541L4GVTLBV8RF",
      "matchId": "02TQ6E3EPS000000VS5489BTVV0LE4BT",
      "side": "away",
      "name": "Felix Altehage",
      "rawName": "๎ฅถ๎ฎท๎นบ๎ตค๎ธ ๎ข๎นบ๎ฃฟ๎บ๎ซฆ๎ญท๎ป๎ฎท",
      "number": "05",
      "img": "https://cdn.fussball.de/public/02VA56IRCS000000VS5489C1VUQPT9H2.stamp",
      "obfuscationKey": "1cpqallx"
    },
    {
      "id": "013RSUNB14000000VV0AG811VSE0VU3I",
      "matchId": "02TQ6E3EPS000000VS5489BTVV0LE4BT",
      "side": "away",
      "name": "Lukas Bergmann",
      "rawName": "๎ดฟ๎ค๎คณ๎ปฃ๎ฌ ๎ถ๎บ๎ญป๎ฑ๎ถซ๎ญท๎ดฑ๎ฅง",
      "number": "07",
      "img": "https://cdn.fussball.de/public/02VKIMPRSC000000VS5489C2VU4VO0A5.stamp",
      "obfuscationKey": "1cpqallx"
    },
    {
      "id": "02UNKLHSRO000000VUM1D57DVSQPUKBN",
      "matchId": "02TQ6E3EPS000000VS5489BTVV0LE4BT",
      "side": "away",
      "name": "Haris Imsirovic",
      "rawName": "๎พข๎ญท๎บญ๎ตค๎ฆ ๎ฌ๎ฝ๎ฆ๎ตค๎ญป๎๎คฌ๎ตค๎ ต",
      "number": "09",
      "img": "https://cdn.fussball.de/public/02VKIND2LC000000VS5489C2VU4VO0A5.stamp",
      "obfuscationKey": "1cpqallx"
    },
    {
      "id": "017JE5J99O000000VV0AG80NVUI4JP8D",
      "matchId": "02TQ6E3EPS000000VS5489BTVV0LE4BT",
      "side": "away",
      "name": "Miles Colin Kappler",
      "rawName": "๎ทบ๎ตค๎นบ๎ฎท๎ฆ ๎ฏฉ๎ฅ๏๎ฏ๎ฅง ๎ธ๎ปฃ๎จข๎จข๏๎ฎท๎ญป",
      "number": "10",
      "img": "https://cdn.fussball.de/public/02VKQCTCSG000000VS5489C0VTURPRAI.stamp",
      "obfuscationKey": "1cpqallx"
    },
    {
      "id": "02K2OPH840000000VUM1DNQ2VU54F1S2",
      "matchId": "02TQ6E3EPS000000VS5489BTVV0LE4BT",
      "side": "away",
      "name": "Fabian Schemme",
      "rawName": "๎ฅถ๎ปฃ๎พป๎ตค๎ญท๎ดฑ ๎ฒ๎ท๎ฟ๎บ๎ฝ๎ถซ๎บ",
      "number": "14",
      "img": "https://images.media.fussball.de/userfiles/p/B/a/5PqJFFh0ub3iajakNf7zi1_p3.jpg",
      "obfuscationKey": "1cpqallx"
    },
    {
      "id": "01R5NDKCQC000000VS541L4JVSBD073C",
      "matchId": "02TQ6E3EPS000000VS5489BTVV0LE4BT",
      "side": "away",
      "name": "Justin Jerome Wrobel",
      "rawName": "๎ก๏๎ฌ๎ฃฟ๎ฏ๎ดฑ ๎ฆฒ๎บ๎ญป๎๎ฝ๎ฎท ๎ฟฏ๎บญ๎ฅ๎ฉ๎บ๎นบ",
      "number": "99",
      "img": "https://cdn.fussball.de/public/02VKIO3NOO000000VS5489C2VU4VO0A5.stamp",
      "obfuscationKey": "1cpqallx"
    },
    {
      "id": "02KEARCCA4000000VUM1DNO9VVTOHQKP",
      "matchId": "02TQ6E3EPS000000VS5489BTVV0LE4BT",
      "side": "away",
      "name": "Phil Kappler",
      "rawName": "๎๎ซฆ๎ตค๎นบ ๎ธ๎ญท๎จข๎ขญ๏๎บ๎บญ",
      "number": "03",
      "img": "https://cdn.fussball.de/public/02S7PG8JR0000000VS5489B1VVVAF4P8.stamp",
      "obfuscationKey": "1cpqallx"
    },
    {
      "id": "00MC739NM8000000VV0AG85VVSMHI0R7",
      "matchId": "02TQ6E3EPS000000VS5489BTVV0LE4BT",
      "side": "away",
      "name": "Mikail Birbir",
      "rawName": "๎ทบ๎ตค๎คณ๎ปฃ๎ฏ๏ ๎น๎ตค๎ญป๎พป๎ฏ๎บญ",
      "number": "04",
      "img": "https://cdn.fussball.de/public/02VKIMST10000000VS5489C2VU4VO0A5.stamp",
      "obfuscationKey": "1cpqallx"
    },
    {
      "id": "02FTBBDBQO000000VUM1DNQAVS4AKOUN",
      "matchId": "02TQ6E3EPS000000VS5489BTVV0LE4BT",
      "side": "away",
      "name": "Henry Jozek",
      "rawName": "๎พข๎ฎท๎ฅง๎บญ๏ ๎ก๎ฅ๎ฎ๎บ๎คณ",
      "number": "17",
      "img": "https://cdn.fussball.de/public/02VKRTPB7C000000VS5489BRVU9AR9BR.stamp",
      "obfuscationKey": "1cpqallx"
    },
    {
      "id": "02BCVRM5OS000000VUM1DNONVTB3KMHT",
      "matchId": "02TQ6E3EPS000000VS5489BTVV0LE4BT",
      "side": "away",
      "name": "Luca Joshua Klein",
      "rawName": "๎ดฟ๎ค๎ท๎ญท ๎ก๎๎ฌ๎ฟ๎ค๎ปฃ ๎ธ๎นบ๎ฎท๎ตค๎ดฑ",
      "number": "29",
      "img": "https://cdn.fussball.de/public/02VKINL2BS000000VS5489C2VU4VO0A5.stamp",
      "obfuscationKey": "1cpqallx"
    },
    {
      "id": "away___",
      "matchId": "02TQ6E3EPS000000VS5489BTVV0LE4BT",
      "side": "away",
      "name": "Seldin Malkoc",
      "rawName": "๎ก๎ฎท๎นบ๎ต๎ตค๎ฅง ๎พ๎ญท๎นบ๎ฎน๎๎ท",
      "number": "",
      "img": "",
      "obfuscationKey": "1cpqallx"
    }
  ],
  "stableId": "02TQ6E3EPS000000VS5489BTVV0LE4BT",
  "generatedAt": "2026-03-20T23:55:27.968Z",
  "game": {
    "home": "SV Zweckel",
    "away": "SC Hassel",
    "date": "15.03.2026",
    "time": "15:00",
    "competition": "Bezirksliga",
    "ageGroup": "Herren",
    "spielId": "02TQ6E3EPS000000VS5489BTVV0LE4BT"
  }
}