{
  "ok": false,
  "error": "lineup_not_available",
  "message": "Waiting for selector `.player-wrapper.home, .player-wrapper.away` failed",
  "matchId": "02TS86HQ78000000VS5489BUVVJ8R9DS",
  "home": "Wacker Gladbeck",
  "away": "SC Hassel III",
  "players": [],
  "stableId": "02TS86HQ78000000VS5489BUVVJ8R9DS",
  "generatedAt": "2026-03-25T10:35:37.754Z",
  "game": {
    "home": "Wacker Gladbeck",
    "away": "SC Hassel III",
    "date": "29.03.2026",
    "time": "15:00",
    "competition": "Kreisliga C",
    "ageGroup": "Herren",
    "spielId": "02TS86HQ78000000VS5489BUVVJ8R9DS"
  }
}