{
  "ok": true,
  "matchId": "02U2A69U98000000VS5489BTVV378D77",
  "url": "https://www.fussball.de/spiel/sc-westfalia-etus-04-31-i-sc-hassel-ii/-/spiel/02U2A69U98000000VS5489BTVV378D77",
  "home": "SC Westfalia ETuS 04/вҖӢ31 I",
  "away": "SC Hassel II",
  "ownSide": "away",
  "count": 8,
  "players": [
    {
      "id": "away___",
      "matchId": "02U2A69U98000000VS5489BTVV378D77",
      "side": "away",
      "name": "Mahmut Aydin",
      "rawName": "оёӮо¬Ҹо»‘оӯ§о»ҡоҹ„ оҹ№оЎ”оіҷо«Ғоіқ",
      "number": "",
      "img": "",
      "obfuscationKey": "vtu73vnl"
    }
  ],
  "stableId": "02U2A69U98000000VS5489BTVV378D77",
  "generatedAt": "2026-04-07T16:43:20.521Z",
  "game": {
    "home": "SC Westfalia ETuS 04/вҖӢ31 I",
    "away": "SC Hassel II",
    "date": "15.11.2025",
    "time": "12:00",
    "competition": "Kreisliga A",
    "ageGroup": "",
    "spielId": "02U2A69U98000000VS5489BTVV378D77"
  }
}