{
  "ok": false,
  "error": "HTTP 500 from http://127.0.0.1:3000/lineup?matchId=02VN5AS57G000000VS5489BTVTG66ASV&home=SC+Hassel+II&away=BV+Rentfort+II&date=21.03.2026&time=12%3A00&competition=Kreisliga+A: {\"ok\":false,\"error\":\"Node is detached from document\",\"players\":[]}",
  "players": [],
  "stableId": "02VN5AS57G000000VS5489BTVTG66ASV",
  "generatedAt": "2026-03-21T11:59:51.995Z",
  "game": {
    "home": "SC Hassel II",
    "away": "BV Rentfort II",
    "date": "21.03.2026",
    "time": "12:00",
    "competition": "Kreisliga A",
    "ageGroup": "D-Junioren",
    "spielId": "02VN5AS57G000000VS5489BTVTG66ASV"
  }
}